secchecker/__init__.py
secchecker/cli.py
secchecker/core.py
secchecker/patterns.py
secchecker/reporter.py
secchecker/secchecker.py
secchecker-0.2.1.dist-info/licenses/LICENSE
secchecker-0.2.1.dist-info/METADATA
secchecker-0.2.1.dist-info/WHEEL
secchecker-0.2.1.dist-info/entry_points.txt
secchecker-0.2.1.dist-info/top_level.txt
secchecker-0.2.1.dist-info/RECORD
