Metadata-Version: 2.4
Name: secchecker
Version: 0.2.1
Summary: A comprehensive CLI tool to detect secrets and sensitive information in repositories for maintaining security best practices.
Author-email: Vishnu Prashanth <vishnu7stanite@gmail.com>
License-Expression: MIT
Project-URL: Homepage, https://github.com/vishnu-77/secchecker
Project-URL: Documentation, https://github.com/vishnu-77/secchecker#readme
Project-URL: Repository, https://github.com/vishnu-77/secchecker.git
Project-URL: Bug Tracker, https://github.com/vishnu-77/secchecker/issues
Project-URL: Changelog, https://github.com/vishnu-77/secchecker/blob/main/CHANGELOG.md
Keywords: security,secrets,devsecops,cli,python,scanning,audit
Classifier: Development Status :: 4 - Beta
Classifier: Intended Audience :: Developers
Classifier: Intended Audience :: Information Technology
Classifier: Topic :: Security
Classifier: Topic :: Security :: Cryptography
Classifier: Topic :: Software Development :: Build Tools
Classifier: Topic :: Software Development :: Quality Assurance
Classifier: Programming Language :: Python :: 3
Classifier: Programming Language :: Python :: 3.8
Classifier: Programming Language :: Python :: 3.9
Classifier: Programming Language :: Python :: 3.10
Classifier: Programming Language :: Python :: 3.11
Classifier: Programming Language :: Python :: 3.12
Classifier: Operating System :: OS Independent
Requires-Python: >=3.8
License-File: LICENSE
Provides-Extra: dev
Requires-Dist: pytest>=6.0; extra == "dev"
Requires-Dist: pytest-cov>=2.0; extra == "dev"
Requires-Dist: flake8>=3.8; extra == "dev"
Requires-Dist: black>=21.0; extra == "dev"
Requires-Dist: mypy>=0.800; extra == "dev"
Provides-Extra: test
Requires-Dist: pytest>=6.0; extra == "test"
Requires-Dist: pytest-cov>=2.0; extra == "test"
Provides-Extra: cli
Requires-Dist: rich>=10.0; extra == "cli"
Dynamic: license-file
